<?xml version="1.0" encoding="UTF-8"?>
<GenRun Id="impl_1" LaunchPart="xc7a35tcpg236-1" LaunchTime="1543442966">
  <File Type="BITSTR-BMM" Name="FA_structural_hw_bd.bmm"/>
  <File Type="OPT-METHODOLOGY-DRC" Name="FA_structural_hw_methodology_drc_opted.rpt"/>
  <File Type="INIT-TIMING" Name="FA_structural_hw_timing_summary_init.rpt"/>
  <File Type="ROUTE-PWR" Name="FA_structural_hw_power_routed.rpt"/>
  <File Type="PA-TCL" Name="FA_structural_hw.tcl"/>
  <File Type="OPT-TIMING" Name="FA_structural_hw_timing_summary_opted.rpt"/>
  <File Type="OPT-DCP" Name="FA_structural_hw_opt.dcp"/>
  <File Type="ROUTE-PWR-SUM" Name="FA_structural_hw_power_summary_routed.pb"/>
  <File Type="REPORTS-TCL" Name="FA_structural_hw_reports.tcl"/>
  <File Type="OPT-DRC" Name="FA_structural_hw_drc_opted.rpt"/>
  <File Type="OPT-HWDEF" Name="FA_structural_hw.hwdef"/>
  <File Type="PWROPT-DCP" Name="FA_structural_hw_pwropt.dcp"/>
  <File Type="PWROPT-DRC" Name="FA_structural_hw_drc_pwropted.rpt"/>
  <File Type="PWROPT-TIMING" Name="FA_structural_hw_timing_summary_pwropted.rpt"/>
  <File Type="PLACE-DCP" Name="FA_structural_hw_placed.dcp"/>
  <File Type="PLACE-IO" Name="FA_structural_hw_io_placed.rpt"/>
  <File Type="PLACE-CLK" Name="FA_structural_hw_clock_utilization_placed.rpt"/>
  <File Type="PLACE-UTIL" Name="FA_structural_hw_utilization_placed.rpt"/>
  <File Type="PLACE-UTIL-PB" Name="FA_structural_hw_utilization_placed.pb"/>
  <File Type="PLACE-CTRL" Name="FA_structural_hw_control_sets_placed.rpt"/>
  <File Type="PLACE-SIMILARITY" Name="FA_structural_hw_incremental_reuse_placed.rpt"/>
  <File Type="PLACE-PRE-SIMILARITY" Name="FA_structural_hw_incremental_reuse_pre_placed.rpt"/>
  <File Type="BG-BGN" Name="FA_structural_hw.bgn"/>
  <File Type="PLACE-TIMING" Name="FA_structural_hw_timing_summary_placed.rpt"/>
  <File Type="POSTPLACE-PWROPT-DCP" Name="FA_structural_hw_postplace_pwropt.dcp"/>
  <File Type="BG-BIN" Name="FA_structural_hw.bin"/>
  <File Type="POSTPLACE-PWROPT-TIMING" Name="FA_structural_hw_timing_summary_postplace_pwropted.rpt"/>
  <File Type="PHYSOPT-DCP" Name="FA_structural_hw_physopt.dcp"/>
  <File Type="PHYSOPT-DRC" Name="FA_structural_hw_drc_physopted.rpt"/>
  <File Type="BITSTR-MSK" Name="FA_structural_hw.msk"/>
  <File Type="PHYSOPT-TIMING" Name="FA_structural_hw_timing_summary_physopted.rpt"/>
  <File Type="ROUTE-ERROR-DCP" Name="FA_structural_hw_routed_error.dcp"/>
  <File Type="ROUTE-DCP" Name="FA_structural_hw_routed.dcp"/>
  <File Type="ROUTE-BLACKBOX-DCP" Name="FA_structural_hw_routed_bb.dcp"/>
  <File Type="ROUTE-DRC" Name="FA_structural_hw_drc_routed.rpt"/>
  <File Type="ROUTE-DRC-PB" Name="FA_structural_hw_drc_routed.pb"/>
  <File Type="BITSTR-LTX" Name="debug_nets.ltx"/>
  <File Type="BITSTR-LTX" Name="FA_structural_hw.ltx"/>
  <File Type="ROUTE-DRC-RPX" Name="FA_structural_hw_drc_routed.rpx"/>
  <File Type="BITSTR-MMI" Name="FA_structural_hw.mmi"/>
  <File Type="ROUTE-METHODOLOGY-DRC" Name="FA_structural_hw_methodology_drc_routed.rpt"/>
  <File Type="ROUTE-METHODOLOGY-DRC-RPX" Name="FA_structural_hw_methodology_drc_routed.rpx"/>
  <File Type="BITSTR-SYSDEF" Name="FA_structural_hw.sysdef"/>
  <File Type="ROUTE-METHODOLOGY-DRC-PB" Name="FA_structural_hw_methodology_drc_routed.pb"/>
  <File Type="ROUTE-PWR-RPX" Name="FA_structural_hw_power_routed.rpx"/>
  <File Type="ROUTE-STATUS" Name="FA_structural_hw_route_status.rpt"/>
  <File Type="ROUTE-STATUS-PB" Name="FA_structural_hw_route_status.pb"/>
  <File Type="ROUTE-TIMINGSUMMARY" Name="FA_structural_hw_timing_summary_routed.rpt"/>
  <File Type="ROUTE-TIMING-PB" Name="FA_structural_hw_timing_summary_routed.pb"/>
  <File Type="ROUTE-TIMING-RPX" Name="FA_structural_hw_timing_summary_routed.rpx"/>
  <File Type="ROUTE-SIMILARITY" Name="FA_structural_hw_incremental_reuse_routed.rpt"/>
  <File Type="ROUTE-CLK" Name="FA_structural_hw_clock_utilization_routed.rpt"/>
  <File Type="ROUTE-BUS-SKEW" Name="FA_structural_hw_bus_skew_routed.rpt"/>
  <File Type="ROUTE-BUS-SKEW-PB" Name="FA_structural_hw_bus_skew_routed.pb"/>
  <File Type="ROUTE-BUS-SKEW-RPX" Name="FA_structural_hw_bus_skew_routed.rpx"/>
  <File Type="POSTROUTE-PHYSOPT-DCP" Name="FA_structural_hw_postroute_physopt.dcp"/>
  <File Type="POSTROUTE-PHYSOPT-BLACKBOX-DCP" Name="FA_structural_hw_postroute_physopt_bb.dcp"/>
  <File Type="POSTROUTE-PHYSOPT-TIMING" Name="FA_structural_hw_timing_summary_postroute_physopted.rpt"/>
  <File Type="POSTROUTE-PHYSOPT-TIMING-PB" Name="FA_structural_hw_timing_summary_postroute_physopted.pb"/>
  <File Type="POSTROUTE-PHYSOPT-TIMING-RPX" Name="FA_structural_hw_timing_summary_postroute_physopted.rpx"/>
  <File Type="POSTROUTE-PHYSOPT-BUS-SKEW" Name="FA_structural_hw_bus_skew_postroute_physopted.rpt"/>
  <File Type="POSTROUTE-PHYSOPT-BUS-SKEW-PB" Name="FA_structural_hw_bus_skew_postroute_physopted.pb"/>
  <File Type="BG-BIT" Name="FA_structural_hw.bit"/>
  <File Type="POSTROUTE-PHYSOPT-BUS-SKEW-RPX" Name="FA_structural_hw_bus_skew_postroute_physopted.rpx"/>
  <File Type="BITSTR-RBT" Name="FA_structural_hw.rbt"/>
  <File Type="BITSTR-NKY" Name="FA_structural_hw.nky"/>
  <File Type="BG-DRC" Name="FA_structural_hw.drc"/>
  <File Type="RDI-RDI" Name="FA_structural_hw.vdi"/>
  <File Type="WBT-USG" Name="usage_statistics_webtalk.html"/>
  <FileSet Name="sources" Type="DesignSrcs" RelSrcDir="$PSRCDIR/sources_1">
    <Filter Type="Srcs"/>
    <File Path="$PSRCDIR/sources_1/new/and2.vhd">
      <FileInfo>
        <Attr Name="UsedIn" Val="synthesis"/>
        <Attr Name="UsedIn" Val="simulation"/>
      </FileInfo>
    </File>
    <File Path="$PSRCDIR/sources_1/new/full_adder_structural.vhd">
      <FileInfo>
        <Attr Name="UsedIn" Val="synthesis"/>
        <Attr Name="UsedIn" Val="simulation"/>
      </FileInfo>
    </File>
    <File Path="$PSRCDIR/sources_1/new/or2.vhd">
      <FileInfo>
        <Attr Name="UsedIn" Val="synthesis"/>
        <Attr Name="UsedIn" Val="simulation"/>
      </FileInfo>
    </File>
    <File Path="$PSRCDIR/sources_1/new/xor2.vhd">
      <FileInfo>
        <Attr Name="UsedIn" Val="synthesis"/>
        <Attr Name="UsedIn" Val="simulation"/>
      </FileInfo>
    </File>
    <File Path="$PSRCDIR/sources_1/new/FA_structural_hw.vhd">
      <FileInfo>
        <Attr Name="UsedIn" Val="synthesis"/>
        <Attr Name="UsedIn" Val="simulation"/>
      </FileInfo>
    </File>
    <Config>
      <Option Name="DesignMode" Val="RTL"/>
      <Option Name="TopModule" Val="FA_structural_hw"/>
    </Config>
  </FileSet>
  <FileSet Name="constrs_in" Type="Constrs" RelSrcDir="$PSRCDIR/constrs_1">
    <Filter Type="Constrs"/>
    <File Path="$PPRDIR/../../Basys3_Master.xdc">
      <FileInfo>
        <Attr Name="UsedIn" Val="synthesis"/>
        <Attr Name="UsedIn" Val="implementation"/>
      </FileInfo>
    </File>
    <Config>
      <Option Name="ConstrsType" Val="XDC"/>
    </Config>
  </FileSet>
  <Strategy Version="1" Minor="2">
    <StratHandle Name="Vivado Implementation Defaults" Flow="Vivado Implementation 2018"/>
    <Step Id="init_design"/>
    <Step Id="opt_design"/>
    <Step Id="power_opt_design"/>
    <Step Id="place_design"/>
    <Step Id="post_place_power_opt_design"/>
    <Step Id="phys_opt_design"/>
    <Step Id="route_design"/>
    <Step Id="post_route_phys_opt_design"/>
    <Step Id="write_bitstream"/>
  </Strategy>
</GenRun>
